adversarial_vision_challenge/VERSION
adversarial_vision_challenge/__init__.py
adversarial_vision_challenge/client.py
adversarial_vision_challenge/common.py
adversarial_vision_challenge/interaction_verifier.py
adversarial_vision_challenge/logger.py
adversarial_vision_challenge/notifier.py
adversarial_vision_challenge/retry_helper.py
adversarial_vision_challenge/server.py
adversarial_vision_challenge/utils.py
adversarial_vision_challenge/test_images/25325656219_26e7657882_o.npy
adversarial_vision_challenge/test_images/26140597434_9b97423b9d_o.npy
adversarial_vision_challenge/test_images/26142687393_8fa6b2ab38_o.npy
adversarial_vision_challenge/test_images/26259480784_8593be720f_o.npy
adversarial_vision_challenge/test_images/26279610183_dc4cd0e676_o.npy
adversarial_vision_challenge/test_images/26330060534_1f92f347e8_o.npy
adversarial_vision_challenge/test_images/26336190203_57ed342fa6_o.npy
adversarial_vision_challenge/test_images/26352465554_bf28d3559e_o.npy
adversarial_vision_challenge/test_images/26365984623_e7a4949bd6_o.npy
adversarial_vision_challenge/test_images/26374515124_09b8dbf998_o.npy
adversarial_vision_challenge/test_images/26406247533_e726668eba_o.npy
adversarial_vision_challenge/test_images/26442708334_59f8072fc4_o.npy
adversarial_vision_challenge/test_images/26454594393_b9b35ccf3a_o.npy
adversarial_vision_challenge/test_images/26479247994_0e1e4f8604_o.npy
adversarial_vision_challenge/test_images/26534483183_dc638c2b29_o.npy
adversarial_vision_challenge/test_images/26539934183_da6ed9c069_o.npy
adversarial_vision_challenge/test_images/26551233133_00febd0008_o.npy
adversarial_vision_challenge/test_images/26551646624_0dafac3dd5_o.npy
adversarial_vision_challenge/test_images/26553223213_1728063546_o.npy
adversarial_vision_challenge/test_images/26594418990_59d679a5b0_o.npy
adversarial_vision_challenge/test_images/26602424463_08b7112b44_o.npy
adversarial_vision_challenge/test_images/26631967370_12e66e4969_o.npy
adversarial_vision_challenge-1.0.5.dist-info/DESCRIPTION.rst
adversarial_vision_challenge-1.0.5.dist-info/METADATA
adversarial_vision_challenge-1.0.5.dist-info/RECORD
adversarial_vision_challenge-1.0.5.dist-info/WHEEL
adversarial_vision_challenge-1.0.5.dist-info/metadata.json
adversarial_vision_challenge-1.0.5.dist-info/top_level.txt
